cratergan/__init__.py
cratergan/__main__.py
cratergan/__version__.py
cratergan/gan.py
cratergan/module/__init__.py
cratergan/module/crater.py
cratergan/module/discriminator.py
cratergan/module/generator.py
cratergan-1.0.2.dist-info/LICENSE
cratergan-1.0.2.dist-info/METADATA
cratergan-1.0.2.dist-info/WHEEL
cratergan-1.0.2.dist-info/top_level.txt
cratergan-1.0.2.dist-info/RECORD
