Metadata-Version: 2.1
Name: cratergan
Version: 1.0.2
Summary: UNKNOWN
Home-page: UNKNOWN
Author: Anton Feldmann
Author-email: anton.feldmann@gmail.com
License: UNKNOWN
Project-URL: Documentations, https://github.com/afeldman/CraterGAN
Project-URL: Source, https://github.com/afeldman/CraterGAN.git
Project-URL: Tracker, https://github.com/afeldman/CraterGAN/issues
Platform: UNKNOWN
License-File: LICENSE
Requires-Dist: torch (==1.10.0)
Requires-Dist: fire (==0.4.0)
Requires-Dist: pytorch-lightning (==1.4.9)
Requires-Dist: numpy (==1.21.2)
Requires-Dist: torchvision (==0.11.1)
Requires-Dist: apu (==0.1.18)
Requires-Dist: craterdata (==0.1.2)
